llama_ocr/__init__.py
llama_ocr/config.py
llama_ocr/core/__init__.py
llama_ocr/core/base.py
llama_ocr/core/extractor.py
llama_ocr/core/image_processor.py
llama_ocr/core/vision_client.py
ollama_vision_extract/__init__.py
ollama_vision_extract/extractor.py
ollama_vision_extract/image_processor.py
ollama_vision_extract/vision_client.py
llama_ocr_py-0.1.0.dist-info/LICENSE
llama_ocr_py-0.1.0.dist-info/METADATA
llama_ocr_py-0.1.0.dist-info/WHEEL
llama_ocr_py-0.1.0.dist-info/top_level.txt
llama_ocr_py-0.1.0.dist-info/RECORD
