Metadata-Version: 2.1
Name: llama_ocr_py
Version: 0.1.0
Summary: A package for document extraction using Ollama Vision model
Home-page: https://github.com/princexoleo/llama_ocr_py
Author: Mazharul Islam Leon
Author-email: Mazharul Islam Leon <xtleon.xl@gmail.com>
License: MIT License
Project-URL: Homepage, https://github.com/princexoleo/llama_ocr
Keywords: ocr,computer vision,document extraction,ollama
Classifier: Programming Language :: Python :: 3
Classifier: License :: OSI Approved :: MIT License
Classifier: Operating System :: OS Independent
Requires-Python: >=3.7
License-File: LICENSE
Requires-Dist: ollama>=0.1.27
Requires-Dist: Pillow>=10.1.0
Requires-Dist: python-dotenv>=1.0.0
Requires-Dist: opencv-python>=4.8.1.78
Requires-Dist: numpy>=1.21.0
